first_principles/__init__.py
first_principles-0.0.0.1.dist-info/LICENSE
first_principles-0.0.0.1.dist-info/METADATA
first_principles-0.0.0.1.dist-info/WHEEL
first_principles-0.0.0.1.dist-info/top_level.txt
first_principles-0.0.0.1.dist-info/RECORD
